paddlesde/__init__.py
paddlesde/settings.py
paddlesde/types.py
paddlesde/_brownian/__init__.py
paddlesde/_brownian/brownian_base.py
paddlesde/_brownian/brownian_interval.py
paddlesde/_brownian/derived.py
paddlesde/_core/__init__.py
paddlesde/_core/adaptive_stepping.py
paddlesde/_core/adjoint.py
paddlesde/_core/adjoint_sde.py
paddlesde/_core/base_sde.py
paddlesde/_core/base_solver.py
paddlesde/_core/better_abc.py
paddlesde/_core/interp.py
paddlesde/_core/misc.py
paddlesde/_core/sdeint.py
paddlesde/_core/methods/__init__.py
paddlesde/_core/methods/euler.py
paddlesde/_core/methods/euler_heun.py
paddlesde/_core/methods/heun.py
paddlesde/_core/methods/log_ode.py
paddlesde/_core/methods/midpoint.py
paddlesde/_core/methods/milstein.py
paddlesde/_core/methods/reversible_heun.py
paddlesde/_core/methods/srk.py
paddlesde/_core/methods/tableaus/__init__.py
paddlesde/_core/methods/tableaus/sra1.py
paddlesde/_core/methods/tableaus/sra2.py
paddlesde/_core/methods/tableaus/sra3.py
paddlesde/_core/methods/tableaus/srid1.py
paddlesde/_core/methods/tableaus/srid2.py
paddlesde-0.2.5.dist-info/LICENSE
paddlesde-0.2.5.dist-info/METADATA
paddlesde-0.2.5.dist-info/WHEEL
paddlesde-0.2.5.dist-info/top_level.txt
paddlesde-0.2.5.dist-info/RECORD
