Metadata-Version: 2.1
Name: paddlesde
Version: 0.2.5
Summary: SDE solvers and stochastic adjoint sensitivity analysis in Paddle.
Home-page: https://github.com/junnyu/paddlesde
Author: Jun Yu
Author-email: 573009727@qq.com
Classifier: Programming Language :: Python :: 3
Classifier: License :: OSI Approved :: Apache Software License
Requires-Python: ~=3.6
License-File: LICENSE
Requires-Dist: boltons (>=20.2.1)
Requires-Dist: trampoline (>=0.1.2)
Requires-Dist: numpy (==1.19) ; python_version < "3.7"
Requires-Dist: scipy (==1.5) ; python_version < "3.7"
Requires-Dist: numpy (>=1.19) ; python_version >= "3.7"
Requires-Dist: scipy (>=1.5) ; python_version >= "3.7"
